[{"id":0,"title":"LADO B #017 – 10 discos para conhecer o City Pop","release_date":"Julho 19, 2021","img":"https://vamosfalarsobremusica.com.br/wp-content/uploads/2021/12/lado_b_17_1-1024x1024.jpg","spotify_url":"about:blank"},{"id":1,"title":"LADO B #016 – 10 filmes de terror com trilhas sonoras assustadoras","release_date":"Maio 3, 2021","img":"https://vamosfalarsobremusica.com.br/wp-content/uploads/2021/12/lado_b_16_1-1024x1024.jpg","spotify_url":"about:blank"},{"id":2,"title":"LADO B #015 – 10 produtores que você precisa conhecer","release_date":"Abril 5, 2021","img":"https://vamosfalarsobremusica.com.br/wp-content/uploads/2021/12/lado_b_15-1024x1024.jpg","spotify_url":"about:blank"},{"id":3,"title":"LADO B #014 – 10 discos para conhecer a série DJ-KICKS","release_date":"Março 1, 2021","img":"https://vamosfalarsobremusica.com.br/wp-content/uploads/2021/12/lado_b_14-1024x1024.jpg","spotify_url":"about:blank"},{"id":4,"title":"LADO B #013 – 10 Discos Para Entender a Chillwave","release_date":"Fevereiro 1, 2021","img":"https://vamosfalarsobremusica.com.br/wp-content/uploads/2021/12/lado_b_13_1-1024x1024.jpg","spotify_url":"about:blank"},{"id":5,"title":"LADO B #012 – 10 discos para conhecer a obra de MF DOOM","release_date":"Janeiro 18, 2021","img":"https://vamosfalarsobremusica.com.br/wp-content/uploads/2021/12/lado_b_12-1024x1024.jpg","spotify_url":"about:blank"},{"id":6,"title":"LADO B #011 – 10 Mulheres Mais Estilosas da Música","release_date":"Janeiro 4, 2021","img":"https://vamosfalarsobremusica.com.br/wp-content/uploads/2021/12/lado_b_11-1024x1024.jpg","spotify_url":"about:blank"},{"id":7,"title":"LADO B #010 – 10 Conexões entre ‘Don’t Start Now’ e a Disco Music","release_date":"Dezembro 14, 2020","img":"https://vamosfalarsobremusica.com.br/wp-content/uploads/2021/12/lado_b_10-1024x1024.jpg","spotify_url":"about:blank"},{"id":8,"title":"LADO B #009 – 10 Discos Para Gostar de Música Eletrônica","release_date":"Novembro 16, 2020","img":"https://vamosfalarsobremusica.com.br/wp-content/uploads/2021/12/lado_b_09-1024x1024.jpg","spotify_url":"about:blank"},{"id":9,"title":"LADO B #008 – 10 Revistas Independentes","release_date":"Outubro 19, 2020","img":"https://vamosfalarsobremusica.com.br/wp-content/uploads/2021/12/lado_b_revistas2-1024x1024.jpg","spotify_url":"about:blank"},{"id":10,"title":"LADO B #007 – 10 Bandas Irlandesas","release_date":"Setembro 14, 2020","img":"https://vamosfalarsobremusica.com.br/wp-content/uploads/2021/12/lado_B_irlanda-1024x1024.jpg","spotify_url":"about:blank"},{"id":11,"title":"LADO B #006- 10 Tiny Desk Concerts Inesquecíveis","release_date":"Agosto 15, 2020","img":"https://vamosfalarsobremusica.com.br/wp-content/uploads/2021/12/lado_b_06-1024x1024.jpg","spotify_url":"about:blank"},{"id":12,"title":"LADO B #005 – 10 Discos Para Gostar de Dream Pop","release_date":"Julho 13, 2020","img":"https://vamosfalarsobremusica.com.br/wp-content/uploads/2021/12/ladoB_dreampop-1024x1024.jpg","spotify_url":"about:blank"},{"id":13,"title":"LADO B #004 – 10 Mulheres Do Indie Rock Que Você Precisa Conhecer","release_date":"Junho 22, 2020","img":"https://vamosfalarsobremusica.com.br/wp-content/uploads/2021/12/lado_b_4-1024x1024.jpg","spotify_url":"about:blank"},{"id":14,"title":"LADO B #003 – 10 Covers Incríveis","release_date":"Maio 19, 2020","img":"https://vamosfalarsobremusica.com.br/wp-content/uploads/2021/12/lado_b_covers-1024x1024.jpg","spotify_url":"about:blank"},{"id":15,"title":"LADO B #002 – 10 Músicas Para Conhecer o Começo do Emo","release_date":"Abril 14, 2020","img":"https://vamosfalarsobremusica.com.br/wp-content/uploads/2021/12/lado_B_emo-1024x1024.jpg","spotify_url":"about:blank"},{"id":16,"title":"LADO B #001 – 10 Discos Para Gostar de Caetano Veloso","release_date":"Março 10, 2020","img":"https://vamosfalarsobremusica.com.br/wp-content/uploads/2021/12/lado_b_capa5-1024x1024.jpg","spotify_url":"about:blank"}]